{
  "uuid": "f231af2c-3130-4c92-b2a0-23d3c2d5ba73",
  "name": "Saby_ИспользоватьЭЛН",
  "name2": {
    "ru": "Saby использовать ЭЛН"
  },
  "comment": "",
  "h1_0": "1",
  "h0": "3",
  "h5": [
    "0",
    "0",
    "00000000-0000-0000-0000-000000000000",
    "0"
  ],
  "data": [
    [
      "1",
      [
        "16",
        [
          "27",
          [
            "2",
            [
              "3",
              [
                "1",
                "0",
                "f231af2c-3130-4c92-b2a0-23d3c2d5ba73"
              ],
              "\"Saby_ИспользоватьЭЛН\"",
              [
                "1",
                "\"ru\"",
                "\"Saby использовать ЭЛН\""
              ],
              "\"\"",
              "0",
              "0",
              "00000000-0000-0000-0000-000000000000",
              "0"
            ],
            [
              "\"Pattern\"",
              [
                "\"B\""
              ]
            ]
          ],
          "0",
          [
            "0"
          ],
          [
            "0"
          ],
          "0",
          "\"\"",
          "0",
          [
            "\"U\""
          ],
          [
            "\"U\""
          ],
          "0",
          "00000000-0000-0000-0000-000000000000",
          "2",
          "0",
          [
            "5006",
            "0"
          ],
          [
            "3",
            "0",
            "0"
          ],
          [
            "0",
            "0"
          ],
          "0",
          [
            "0"
          ],
          [
            "\"S\"",
            "\"\""
          ],
          "0",
          "0",
          "0"
        ],
        "dddf4c3b-bb15-4203-ae3c-b160f0705bb3",
        "f9323128-310f-4573-9510-c5fe5d69d53e",
        "fc3088d7-b2dd-4808-a673-634f3c8e8b6a",
        "74466c40-0804-4618-98fc-a05aa912b9a9",
        "1",
        "1",
        [
          "0"
        ],
        [
          "0"
        ],
        "00000000-0000-0000-0000-000000000000",
        "0",
        "0",
        "0f342008-bcbb-4df6-9ae5-235cd4de8fc1",
        "93eeeff3-d8bd-4e2a-90fa-8aaf165bb083",
        "0",
        "0"
      ],
      "0"
    ]
  ],
  "code_info_mgr": "file",
  "code_encoding_mgr": "utf-8",
  "code_info_obj": "file",
  "code_encoding_obj": "utf-8"
}